Workbook
Name base_rev: assumptions!$B$18
Name cogs_pct: assumptions!$B$20
Name depreciation: assumptions!$B$25
Name mktg_pct: assumptions!$B$24
Name payroll: assumptions!$B$21
Name payroll_growth: assumptions!$B$22
Name py_ebit: assumptions!$B$28
Name py_rev: assumptions!$B$27
Name rent: assumptions!$B$23
Name rev_growth: assumptions!$B$19
Name tax_rate: assumptions!$B$26

Sheet assumptions
A1: =========================================
A2: FY2025 Budget Model
A3: Company: Zona LPJ
A4: Author: Lintang Permata Jati
A5: Built: Day 14 of 30-Day Finance Analyst
A6: Version: v1.0
A7: Last updated: 21 April 2026
A8: =========================================
A9: Assumptions:
A10: - Revenue grows 2% MoM from an 80,000 Jan base
A11: - COGS fixed at 38% of revenue
A12: - Payroll grows 0.5% MoM
... A15: =========================================
A17: LABEL | B17: VALUE
A18: Base monthly revenue (Jan) | B18: 80000
A19: Monthly revenue growth rate | B19: 0.02
A20: COGS % of revenue | B20: 0.38
A21: Gross payroll (monthly) | B21: 25000
A22: Payroll growth (monthly) | B22: 0.005
A23: Rent (fixed monthly) | B23: 8000
A24: Marketing % of revenue | B24: 0.05
A25: Depreciation (monthly) | B25: 3000
A26: Tax rate | B26: 0.28
A27: Prior year total revenue | B27: 900000
A28: Prior year total EBIT | B28: 95000

Sheet monthly_pl
A1: Line Item | B1: Jan | C1: Feb | D1: Mar | E1: Apr | F1: May | G1: Jun | H1: Jul | I1: Aug | J1: Sep | K1: Oct | L1: Nov | M1: Dec | N1: Full Year
A2: Revenue | B2: =base_rev -> 80000 | C2: =B2*(1+rev_growth) -> 81600 | D2: =C2*(1+rev_growth) -> 83232 | E2: =D2*(1+rev_growth) -> 84896.64 | F2: =E2*(1+rev_growth) -> 86594.573 | G2: =F2*(1+rev_growth) -> 88326.464 | H2: =G2*(1+rev_growth) -> 90092.994 | I2: =H2*(1+rev_growth) -> 91894.853 | J2: =I2*(1+rev_growth) -> 93732.75 | ... M2: =L2*(1+rev_growth) -> 99469.945 | N2: =SUM(B2:M2) -> 1072967.2
A3: COGS | B3: =-B2*cogs_pct -> -30400 | C3: =-C2*cogs_pct -> -31008 | D3: =-D2*cogs_pct -> -31628.16 | E3: =-E2*cogs_pct -> -32260.723 | F3: =-F2*cogs_pct -> -32905.938 | G3: =-G2*cogs_pct -> -33564.056 | H3: =-H2*cogs_pct -> -34235.338 | I3: =-I2*cogs_pct -> -34920.044 | ... M3: =-M2*cogs_pct -> -37798.579 | N3: =SUM(B3:M3) -> -407727.53
A4: Gross Profit | B4: =B2+B3 -> 49600 | C4: =C2+C3 -> 50592 | D4: =D2+D3 -> 51603.84 | E4: =E2+E3 -> 52635.917 | F4: =F2+F3 -> 53688.635 | G4: =G2+G3 -> 54762.408 | H4: =H2+H3 -> 55857.656 | I4: =I2+I3 -> 56974.809 | ... M4: =M2+M3 -> 61671.366 | N4: =SUM(B4:M4) -> 665239.65
A6: Payroll | B6: =-payroll -> -25000 | C6: =B6*(1+payroll_growth) -> -25125 | D6: =C6*(1+payroll_growth) -> -25250.625 | E6: =D6*(1+payroll_growth) -> -25376.878 | F6: =E6*(1+payroll_growth) -> -25503.763 | G6: =F6*(1+payroll_growth) -> -25631.281 | H6: =G6*(1+payroll_growth) -> -25759.438 | I6: =H6*(1+payroll_growth) -> -25888.235 | J6: =I6*(1+payroll_growth) -> -26017.676 | ... M6: =L6*(1+payroll_growth) -> -26409.896 | N6: =SUM(B6:M6) -> -308389.06
A7: Rent | B7: =-rent -> -8000 | C7: =-rent -> -8000 | D7: =-rent -> -8000 | E7: =-rent -> -8000 | F7: =-rent -> -8000 | G7: =-rent -> -8000 | H7: =-rent -> -8000 | I7: =-rent -> -8000 | ... M7: =-rent -> -8000 | N7: =SUM(B7:M7) -> -96000
A8: Marketing | B8: =-B2*mktg_pct -> -4000 | C8: =-C2*mktg_pct -> -4080 | D8: =-D2*mktg_pct -> -4161.6 | E8: =-E2*mktg_pct -> -4244.832 | F8: =-F2*mktg_pct -> -4329.7286 | G8: =-G2*mktg_pct -> -4416.3232 | H8: =-H2*mktg_pct -> -4504.6497 | I8: =-I2*mktg_pct -> -4594.7427 | ... M8: =-M2*mktg_pct -> -4973.4972 | N8: =SUM(B8:M8) -> -53648.359
A9: Depreciation | B9: =-depreciation -> -3000 | C9: =-depreciation -> -3000 | D9: =-depreciation -> -3000 | E9: =-depreciation -> -3000 | F9: =-depreciation -> -3000 | G9: =-depreciation -> -3000 | H9: =-depreciation -> -3000 | I9: =-depreciation -> -3000 | ... M9: =-depreciation -> -3000 | N9: =SUM(B9:M9) -> -36000
A10: Total OpEx | B10: =SUM(B6:B9) -> -40000 | C10: =SUM(C6:C9) -> -40205 | D10: =SUM(D6:D9) -> -40412.225 | E10: =SUM(E6:E9) -> -40621.71 | F10: =SUM(F6:F9) -> -40833.491 | G10: =SUM(G6:G9) -> -41047.605 | H10: =SUM(H6:H9) -> -41264.087 | I10: =SUM(I6:I9) -> -41482.978 | ... M10: =SUM(M6:M9) -> -42383.393 | N10: =SUM(B10:M10) -> -494037.42
A12: EBIT | B12: =B4+B10 -> 9600 | C12: =C4+C10 -> 10387 | D12: =D4+D10 -> 11191.615 | E12: =E4+E10 -> 12014.207 | F12: =F4+F10 -> 12855.144 | G12: =G4+G10 -> 13714.803 | H12: =H4+H10 -> 14593.569 | I12: =I4+I10 -> 15491.832 | ... M12: =M4+M10 -> 19287.973 | N12: =SUM(B12:M12) -> 171202.23
A13: Tax | B13: =-B12*tax_rate -> -2688 | C13: =-C12*tax_rate -> -2908.36 | D13: =-D12*tax_rate -> -3133.6522 | E13: =-E12*tax_rate -> -3363.9779 | F13: =-F12*tax_rate -> -3599.4403 | G13: =-G12*tax_rate -> -3840.1449 | H13: =-H12*tax_rate -> -4086.1992 | I13: =-I12*tax_rate -> -4337.7128 | ... M13: =-M12*tax_rate -> -5400.6323 | N13: =SUM(B13:M13) -> -47936.625
A14: Net Income | B14: =B12+B13 -> 6912 | C14: =C12+C13 -> 7478.64 | D14: =D12+D13 -> 8057.9628 | E14: =E12+E13 -> 8650.2288 | F14: =F12+F13 -> 9255.7037 | G14: =G12+G13 -> 9874.6584 | H14: =H12+H13 -> 10507.369 | I14: =I12+I13 -> 11154.119 | ... M14: =M12+M13 -> 13887.34 | N14: =SUM(B14:M14) -> 123265.61
A16: CHECK: EBIT = GP + OpEx | B16: =IF(B12=B4+B10, "OK", "ERROR") -> OK | C16: =IF(C12=C4+C10, "OK", "ERROR") -> OK | D16: =IF(D12=D4+D10, "OK", "ERROR") -> OK | E16: =IF(E12=E4+E10, "OK", "ERROR") -> OK | F16: =IF(F12=F4+F10, "OK", "ERROR") -> OK | G16: =IF(G12=G4+G10, "OK", "ERROR") -> OK | H16: =IF(H12=H4+H10, "OK", "ERROR") -> OK | I16: =IF(I12=I4+I10, "OK", "ERROR") -> OK | ... M16: =IF(M12=M4+M10, "OK", "ERROR") -> OK | N16: =COUNTIF(B16:M16, "ERROR") -> 0

Sheet prior_year
A1: Line Item | B1: FY2024 Actual
A2: Revenue | B2: 900000
A3: COGS | B3: -342000
A4: Gross Profit | B4: 558000
A6: Payroll | B6: -275000
A7: Rent | B7: -90000
A8: Marketing | B8: -45000
A9: Depreciation | B9: -33000
A10: Total OpEx | B10: -443000
A12: EBIT | B12: 115000
A13: Tax | B13: -32200
A14: Net Income | B14: 82800

Sheet variance
B1: FY2025 Budget | C1: FY2024 Actual | D1: $ Variance | E1: % Variance | F1: Flag
A2: Revenue | B2: =monthly_pl!N2 -> 1072967.2 | C2: =prior_year!B2 -> 900000 | D2: =B2-C2 -> 172967.18 | E2: =IFERROR(D2/ABS(C2), 0) -> 0.19218575 | F2: =IF(ABS(E2)>0.5, "Critical", IF(ABS(E2)>0.1, "Significant", "Normal")) -> Significant
A3: COGS | B3: =monthly_pl!N3 -> -407727.53 | C3: =prior_year!B3 -> -342000 | D3: =B3-C3 -> -65727.528 | E3: =IFERROR(D3/ABS(C3), 0) -> -0.19218575 | F3: =IF(ABS(E3)>0.5, "Critical", IF(ABS(E3)>0.1, "Significant", "Normal")) -> Significant
A4: Gross Profit | B4: =monthly_pl!N4 -> 665239.65 | C4: =prior_year!B4 -> 558000 | D4: =B4-C4 -> 107239.65 | E4: =IFERROR(D4/ABS(C4), 0) -> 0.19218575 | F4: =IF(ABS(E4)>0.5, "Critical", IF(ABS(E4)>0.1, "Significant", "Normal")) -> Significant
A5: Payroll | B5: =monthly_pl!N6 -> -308389.06 | C5: =prior_year!B6 -> -275000 | D5: =B5-C5 -> -33389.059 | E5: =IFERROR(D5/ABS(C5), 0) -> -0.12141476 | F5: =IF(ABS(E5)>0.5, "Critical", IF(ABS(E5)>0.1, "Significant", "Normal")) -> Significant
A6: Rent | B6: =monthly_pl!N7 -> -96000 | C6: =prior_year!B7 -> -90000 | D6: =B6-C6 -> -6000 | E6: =IFERROR(D6/ABS(C6), 0) -> -0.066666667 | F6: =IF(ABS(E6)>0.5, "Critical", IF(ABS(E6)>0.1, "Significant", "Normal")) -> Normal
A7: Marketing | B7: =monthly_pl!N8 -> -53648.359 | C7: =prior_year!B8 -> -45000 | D7: =B7-C7 -> -8648.3589 | E7: =IFERROR(D7/ABS(C7), 0) -> -0.19218575 | F7: =IF(ABS(E7)>0.5, "Critical", IF(ABS(E7)>0.1, "Significant", "Normal")) -> Significant
A8: Depreciation | B8: =monthly_pl!N9 -> -36000 | C8: =prior_year!B9 -> -33000 | D8: =B8-C8 -> -3000 | E8: =IFERROR(D8/ABS(C8), 0) -> -0.090909091 | F8: =IF(ABS(E8)>0.5, "Critical", IF(ABS(E8)>0.1, "Significant", "Normal")) -> Normal
A9: Total OpEx | B9: =monthly_pl!N10 -> -494037.42 | C9: =prior_year!B10 -> -443000 | D9: =B9-C9 -> -51037.418 | E9: =IFERROR(D9/ABS(C9), 0) -> -0.11520862 | F9: =IF(ABS(E9)>0.5, "Critical", IF(ABS(E9)>0.1, "Significant", "Normal")) -> Significant
A10: EBIT | B10: =monthly_pl!N12 -> 171202.23 | C10: =prior_year!B12 -> 115000 | D10: =B10-C10 -> 56202.232 | E10: =IFERROR(D10/ABS(C10), 0) -> 0.48871506 | F10: =IF(ABS(E10)>0.5, "Critical", IF(ABS(E10)>0.1, "Significant", "Normal")) -> Significant
A11: Tax | B11: =monthly_pl!N13 -> -47936.625 | C11: =prior_year!B13 -> -32200 | D11: =B11-C11 -> -15736.625 | E11: =IFERROR(D11/ABS(C11), 0) -> -0.48871506 | F11: =IF(ABS(E11)>0.5, "Critical", IF(ABS(E11)>0.1, "Significant", "Normal")) -> Significant
A12: Net Income | B12: =monthly_pl!N14 -> 123265.61 | C12: =prior_year!B14 -> 82800 | D12: =B12-C12 -> 40465.607 | E12: =IFERROR(D12/ABS(C12), 0) -> 0.48871506 | F12: =IF(ABS(E12)>0.5, "Critical", IF(ABS(E12)>0.1, "Significant", "Normal")) -> Significant
